RandoRank-0.1.3.dist-info/METADATA
RandoRank-0.1.3.dist-info/WHEEL
randorank.cpython-36m-x86_64-linux-gnu.so
RandoRank-0.1.3.dist-info/RECORD
